<?xml version="1.0" encoding="utf-8"?>
<TextureAtlas imagePath="sexGf.png">
	<!-- Created with Adobe Animate version 19.0.0.326 -->
	<!-- http://www.adobe.com/products/animate.html -->
	<SubTexture name="Gf_Idle0000" x="3" y="3" width="534" height="695"/>
	<SubTexture name="Gf_Idle0001" x="3" y="3" width="534" height="695"/>
	<SubTexture name="Gf_Idle0002" x="542" y="3" width="534" height="695"/>
	<SubTexture name="Gf_Idle0003" x="542" y="3" width="534" height="695"/>
	<SubTexture name="Gf_Idle0004" x="542" y="3" width="534" height="695"/>
	<SubTexture name="Gf_Idle0005" x="1081" y="3" width="534" height="695"/>
	<SubTexture name="Gf_Idle0006" x="1081" y="3" width="534" height="695"/>
	<SubTexture name="Gf_Idle0007" x="1081" y="3" width="534" height="695"/>
	<SubTexture name="Gf_Idle0008" x="3" y="3" width="534" height="695"/>
	<SubTexture name="Gf_Idle0009" x="3" y="3" width="534" height="695"/>
	<SubTexture name="Gf_Idle0010" x="3" y="3" width="534" height="695"/>
	<SubTexture name="Gf_Idle0011" x="542" y="3" width="534" height="695"/>
	<SubTexture name="Gf_Idle0012" x="542" y="3" width="534" height="695"/>
	<SubTexture name="Gf_Idle0013" x="542" y="3" width="534" height="695"/>
	<SubTexture name="Gf_down0000" x="1620" y="3" width="609" height="713"/>
	<SubTexture name="Gf_down0001" x="1620" y="3" width="609" height="713"/>
	<SubTexture name="Gf_down0002" x="2234" y="3" width="609" height="713"/>
	<SubTexture name="Gf_down0003" x="2234" y="3" width="609" height="713"/>
	<SubTexture name="Gf_down0004" x="2848" y="3" width="609" height="713"/>
	<SubTexture name="Gf_down0005" x="2848" y="3" width="609" height="713"/>
	<SubTexture name="Gf_down0006" x="2848" y="3" width="609" height="713"/>
	<SubTexture name="Gf_down0007" x="2848" y="3" width="609" height="713"/>
	<SubTexture name="Gf_down0008" x="2848" y="3" width="609" height="713"/>
	<SubTexture name="Gf_down0009" x="2848" y="3" width="609" height="713"/>
	<SubTexture name="Gf_down0010" x="2848" y="3" width="609" height="713"/>
	<SubTexture name="Gf_down0011" x="2848" y="3" width="609" height="713"/>
	<SubTexture name="Gf_down0012" x="2848" y="3" width="609" height="713"/>
	<SubTexture name="Gf_down0013" x="2848" y="3" width="609" height="713"/>
	<SubTexture name="Gf_left0000" x="3462" y="3" width="560" height="700"/>
	<SubTexture name="Gf_left0001" x="3462" y="3" width="560" height="700"/>
	<SubTexture name="Gf_left0002" x="3" y="721" width="560" height="700"/>
	<SubTexture name="Gf_left0003" x="3" y="721" width="560" height="700"/>
	<SubTexture name="Gf_left0004" x="568" y="721" width="560" height="700"/>
	<SubTexture name="Gf_left0005" x="568" y="721" width="560" height="700"/>
	<SubTexture name="Gf_left0006" x="568" y="721" width="560" height="700"/>
	<SubTexture name="Gf_left0007" x="568" y="721" width="560" height="700"/>
	<SubTexture name="Gf_left0008" x="568" y="721" width="560" height="700"/>
	<SubTexture name="Gf_left0009" x="568" y="721" width="560" height="700"/>
	<SubTexture name="Gf_left0010" x="568" y="721" width="560" height="700"/>
	<SubTexture name="Gf_left0011" x="568" y="721" width="560" height="700"/>
	<SubTexture name="Gf_left0012" x="568" y="721" width="560" height="700"/>
	<SubTexture name="Gf_left0013" x="568" y="721" width="560" height="700"/>
	<SubTexture name="Gf_right0000" x="1133" y="721" width="630" height="706"/>
	<SubTexture name="Gf_right0001" x="1133" y="721" width="630" height="706"/>
	<SubTexture name="Gf_right0002" x="1768" y="721" width="630" height="706"/>
	<SubTexture name="Gf_right0003" x="1768" y="721" width="630" height="706"/>
	<SubTexture name="Gf_right0004" x="2403" y="721" width="630" height="706"/>
	<SubTexture name="Gf_right0005" x="2403" y="721" width="630" height="706"/>
	<SubTexture name="Gf_right0006" x="3038" y="721" width="630" height="706"/>
	<SubTexture name="Gf_right0007" x="3038" y="721" width="630" height="706"/>
	<SubTexture name="Gf_right0008" x="3038" y="721" width="630" height="706"/>
	<SubTexture name="Gf_right0009" x="3038" y="721" width="630" height="706"/>
	<SubTexture name="Gf_right0010" x="3038" y="721" width="630" height="706"/>
	<SubTexture name="Gf_right0011" x="3038" y="721" width="630" height="706"/>
	<SubTexture name="Gf_right0012" x="3038" y="721" width="630" height="706"/>
	<SubTexture name="Gf_right0013" x="3038" y="721" width="630" height="706"/>
	<SubTexture name="Gf_up0000" x="3" y="1432" width="625" height="709"/>
	<SubTexture name="Gf_up0001" x="3" y="1432" width="625" height="709"/>
	<SubTexture name="Gf_up0002" x="633" y="1432" width="625" height="709"/>
	<SubTexture name="Gf_up0003" x="633" y="1432" width="625" height="709"/>
	<SubTexture name="Gf_up0004" x="1263" y="1432" width="625" height="709"/>
	<SubTexture name="Gf_up0005" x="1263" y="1432" width="625" height="709"/>
	<SubTexture name="Gf_up0006" x="1893" y="1432" width="625" height="709"/>
	<SubTexture name="Gf_up0007" x="1893" y="1432" width="625" height="709"/>
	<SubTexture name="Gf_up0008" x="1893" y="1432" width="625" height="709"/>
	<SubTexture name="Gf_up0009" x="1893" y="1432" width="625" height="709"/>
	<SubTexture name="Gf_up0010" x="1893" y="1432" width="625" height="709"/>
	<SubTexture name="Gf_up0011" x="1893" y="1432" width="625" height="709"/>
	<SubTexture name="Gf_up0012" x="1893" y="1432" width="625" height="709"/>
	<SubTexture name="Gf_up0013" x="1893" y="1432" width="625" height="709"/>
	<SubTexture name="miss_down0000" x="2523" y="1432" width="597" height="647"/>
	<SubTexture name="miss_down0001" x="2523" y="1432" width="597" height="647"/>
	<SubTexture name="miss_down0002" x="3125" y="1432" width="597" height="647"/>
	<SubTexture name="miss_down0003" x="3" y="2146" width="597" height="647"/>
	<SubTexture name="miss_down0004" x="605" y="2146" width="597" height="647"/>
	<SubTexture name="miss_down0005" x="3125" y="1432" width="597" height="647"/>
	<SubTexture name="miss_down0006" x="3" y="2146" width="597" height="647"/>
	<SubTexture name="miss_down0007" x="605" y="2146" width="597" height="647"/>
	<SubTexture name="miss_down0008" x="3125" y="1432" width="597" height="647"/>
	<SubTexture name="miss_down0009" x="3" y="2146" width="597" height="647"/>
	<SubTexture name="miss_down0010" x="605" y="2146" width="597" height="647"/>
	<SubTexture name="miss_down0011" x="3125" y="1432" width="597" height="647"/>
	<SubTexture name="miss_down0012" x="3" y="2146" width="597" height="647"/>
	<SubTexture name="miss_down0013" x="605" y="2146" width="597" height="647"/>
	<SubTexture name="miss_left0000" x="1207" y="2146" width="541" height="689"/>
	<SubTexture name="miss_left0001" x="1207" y="2146" width="541" height="689"/>
	<SubTexture name="miss_left0002" x="1753" y="2146" width="541" height="689"/>
	<SubTexture name="miss_left0003" x="2299" y="2146" width="541" height="689"/>
	<SubTexture name="miss_left0004" x="2845" y="2146" width="541" height="689"/>
	<SubTexture name="miss_left0005" x="1753" y="2146" width="541" height="689"/>
	<SubTexture name="miss_left0006" x="2299" y="2146" width="541" height="689"/>
	<SubTexture name="miss_left0007" x="2845" y="2146" width="541" height="689"/>
	<SubTexture name="miss_left0008" x="1753" y="2146" width="541" height="689"/>
	<SubTexture name="miss_left0009" x="2299" y="2146" width="541" height="689"/>
	<SubTexture name="miss_left0010" x="2845" y="2146" width="541" height="689"/>
	<SubTexture name="miss_left0011" x="1753" y="2146" width="541" height="689"/>
	<SubTexture name="miss_left0012" x="2299" y="2146" width="541" height="689"/>
	<SubTexture name="miss_left0013" x="2845" y="2146" width="541" height="689"/>
	<SubTexture name="miss_right0000" x="3391" y="2146" width="559" height="684"/>
	<SubTexture name="miss_right0001" x="3391" y="2146" width="559" height="684"/>
	<SubTexture name="miss_right0002" x="3" y="2840" width="559" height="684"/>
	<SubTexture name="miss_right0003" x="567" y="2840" width="559" height="684"/>
	<SubTexture name="miss_right0004" x="1131" y="2840" width="559" height="684"/>
	<SubTexture name="miss_right0005" x="3" y="2840" width="559" height="684"/>
	<SubTexture name="miss_right0006" x="567" y="2840" width="559" height="684"/>
	<SubTexture name="miss_right0007" x="1131" y="2840" width="559" height="684"/>
	<SubTexture name="miss_right0008" x="3" y="2840" width="559" height="684"/>
	<SubTexture name="miss_right0009" x="567" y="2840" width="559" height="684"/>
	<SubTexture name="miss_right0010" x="1131" y="2840" width="559" height="684"/>
	<SubTexture name="miss_right0011" x="3" y="2840" width="559" height="684"/>
	<SubTexture name="miss_right0012" x="567" y="2840" width="559" height="684"/>
	<SubTexture name="miss_right0013" x="1131" y="2840" width="559" height="684"/>
	<SubTexture name="miss_up0000" x="1695" y="2840" width="584" height="724"/>
	<SubTexture name="miss_up0001" x="1695" y="2840" width="584" height="724"/>
	<SubTexture name="miss_up0002" x="2284" y="2840" width="584" height="724"/>
	<SubTexture name="miss_up0003" x="2873" y="2840" width="584" height="724"/>
	<SubTexture name="miss_up0004" x="3462" y="2840" width="584" height="724"/>
	<SubTexture name="miss_up0005" x="2284" y="2840" width="584" height="724"/>
	<SubTexture name="miss_up0006" x="2873" y="2840" width="584" height="724"/>
	<SubTexture name="miss_up0007" x="3462" y="2840" width="584" height="724"/>
	<SubTexture name="miss_up0008" x="2284" y="2840" width="584" height="724"/>
	<SubTexture name="miss_up0009" x="2873" y="2840" width="584" height="724"/>
	<SubTexture name="miss_up0010" x="3462" y="2840" width="584" height="724"/>
	<SubTexture name="miss_up0011" x="2284" y="2840" width="584" height="724"/>
	<SubTexture name="miss_up0012" x="2873" y="2840" width="584" height="724"/>
	<SubTexture name="miss_up0013" x="3462" y="2840" width="584" height="724"/>
</TextureAtlas>
